igwn_gwalert_schema/__init__.py
igwn_gwalert_schema/igwn.alerts.v1_0.Alert.avsc
igwn_gwalert_schema/igwn.alerts.v1_0.Alert.schema.json
igwn_gwalert_schema/igwn.alerts.v1_0.AlertType.avsc
igwn_gwalert_schema/igwn.alerts.v1_0.EventInfo.avsc
igwn_gwalert_schema/igwn.alerts.v1_0.ExternalCoincInfo.avsc
igwn_gwalert_schema-1.0.0.dist-info/LICENSE.md
igwn_gwalert_schema-1.0.0.dist-info/METADATA
igwn_gwalert_schema-1.0.0.dist-info/WHEEL
igwn_gwalert_schema-1.0.0.dist-info/top_level.txt
igwn_gwalert_schema-1.0.0.dist-info/RECORD
