Metadata-Version: 2.1
Name: igwn-gwalert-schema
Version: 1.0.0
Summary: JSON and Avro Schema for gravitational-wave alerts
Author-email: Leo Singer <leo.p.singer@nasa.gov>, Cody Messick <cody.messick@ligo.org>
License: GPL-3+
Project-URL: source, https://git.ligo.org/emfollow/igwn-gwalert-schema
Project-URL: Bug Tracker, https://git.ligo.org/emfollow/igwn-gwalert-schema/issues
Project-URL: Source Code, https://git.ligo.org/emfollow/igwn-gwalert-schema
Classifier: Development Status :: 4 - Beta
Classifier: Intended Audience :: Science/Research
Classifier: License :: OSI Approved :: GNU General Public License v3 or later (GPLv3+)
Classifier: Programming Language :: Python :: 3
Classifier: Programming Language :: Python :: 3.8
Classifier: Programming Language :: Python :: 3.9
Classifier: Programming Language :: Python :: 3.10
Classifier: Programming Language :: Python :: 3.11
Classifier: Topic :: Internet
Classifier: Topic :: Scientific/Engineering :: Astronomy
Classifier: Topic :: Scientific/Engineering :: Physics
Requires-Python: >=3.8
License-File: LICENSE.md
